[{"country": "United States", "sessions": "112612"}, {"country": "Canada", "sessions": "1890"}, {"country": "Netherlands", "sessions": "901"}, {"country": "United Kingdom", "sessions": "388"}, {"country": "Denmark", "sessions": "381"}, {"country": "Italy", "sessions": "320"}, {"country": "Mexico", "sessions": "280"}, {"country": "France", "sessions": "258"}, {"country": "Brazil", "sessions": "181"}, {"country": "Japan", "sessions": "136"}, {"country": "Turkey", "sessions": "127"}, {"country": "Australia", "sessions": "125"}, {"country": "Germany", "sessions": "109"}, {"country": "Spain", "sessions": "102"}, {"country": "Russian Federation", "sessions": "94"}, {"country": "China", "sessions": "77"}, {"country": "Pakistan", "sessions": "71"}, {"country": "Sweden", "sessions": "69"}, {"country": "United Arab Emirates", "sessions": "67"}, {"country": "Thailand", "sessions": "58"}, {"country": "Switzerland", "sessions": "55"}, {"country": "Belgium", "sessions": "51"}, {"country": "Saudi Arabia", "sessions": "49"}, {"country": "India", "sessions": "46"}, {"country": "Puerto Rico", "sessions": "44"}, {"country": "Kuwait", "sessions": "43"}, {"country": "Republic of Korea", "sessions": "41"}, {"country": "Lao People's Democratic Republic", "sessions": "38"}, {"country": "Portugal", "sessions": "38"}, {"country": "Singapore", "sessions": "36"}, {"country": "Ireland", "sessions": "32"}, {"country": "Nicaragua", "sessions": "31"}, {"country": "Guatemala", "sessions": "30"}, {"country": "Israel", "sessions": "29"}, {"country": "Greece", "sessions": "29"}, {"country": "Norway", "sessions": "29"}, {"country": "Hong Kong", "sessions": "28"}, {"country": "Malaysia", "sessions": "27"}, {"country": "Romania", "sessions": "24"}, {"country": "Hungary", "sessions": "24"}, {"country": "Republic of Moldova", "sessions": "24"}, {"country": "Venezuela", "sessions": "21"}, {"country": "Chile", "sessions": "20"}, {"country": "Colombia", "sessions": "20"}, {"country": "Philippines", "sessions": "19"}, {"country": "New Zealand", "sessions": "19"}, {"country": "Taiwan", "sessions": "19"}, {"country": "Argentina", "sessions": "19"}, {"country": "Peru", "sessions": "17"}, {"country": "Honduras", "sessions": "17"}, {"country": "South Africa", "sessions": "16"}, {"country": "Costa Rica", "sessions": "15"}, {"country": "Qatar", "sessions": "14"}, {"country": "Poland", "sessions": "13"}, {"country": "British Virgin Islands", "sessions": "13"}, {"country": "Dominican Republic", "sessions": "13"}, {"country": "Haiti", "sessions": "13"}, {"country": "Ukraine", "sessions": "12"}, {"country": "Bermuda", "sessions": "11"}, {"country": "Islamic Republic of Iran", "sessions": "11"}, {"country": "Ecuador", "sessions": "11"}, {"country": "Panama", "sessions": "11"}, {"country": "Serbia", "sessions": "11"}, {"country": "Nigeria", "sessions": "10"}, {"country": "US Virgin Islands", "sessions": "10"}, {"country": "Croatia", "sessions": "9"}, {"country": "Uruguay", "sessions": "9"}, {"country": "Afghanistan", "sessions": "9"}, {"country": "Austria", "sessions": "9"}, {"country": "Morocco", "sessions": "8"}, {"country": "Lebanon", "sessions": "8"}, {"country": "Latvia", "sessions": "8"}, {"country": "Bulgaria", "sessions": "7"}, {"country": "Bahrain", "sessions": "6"}, {"country": "Oman", "sessions": "6"}, {"country": "Trinidad and Tobago", "sessions": "6"}, {"country": "Egypt", "sessions": "6"}, {"country": "Kenya", "sessions": "6"}, {"country": "Saint Kitts and Nevis", "sessions": "6"}, {"country": "Guam", "sessions": "5"}, {"country": "Luxembourg", "sessions": "5"}, {"country": "Greenland", "sessions": "5"}, {"country": "Bolivia", "sessions": "4"}, {"country": "Slovenia", "sessions": "4"}, {"country": "Guadeloupe", "sessions": "4"}, {"country": "Czech Republic", "sessions": "3"}, {"country": "Iraq", "sessions": "3"}, {"country": "Armenia", "sessions": "3"}, {"country": "French Polynesia", "sessions": "3"}, {"country": "Bangladesh", "sessions": "3"}, {"country": "Palestinian Territory", "sessions": "2"}, {"country": "Liechtenstein", "sessions": "2"}, {"country": "Nepal", "sessions": "2"}, {"country": "Bahamas", "sessions": "2"}, {"country": "Rwanda", "sessions": "2"}, {"country": "Iceland", "sessions": "2"}, {"country": "Saint Vincent and the Grenadines", "sessions": "2"}, {"country": "Indonesia", "sessions": "2"}, {"country": "Macedonia", "sessions": "2"}, {"country": "Montenegro", "sessions": "2"}, {"country": "Finland", "sessions": "2"}, {"country": "Mali", "sessions": "2"}, {"country": "Albania", "sessions": "2"}, {"country": "Jamaica", "sessions": "1"}, {"country": "Jordan", "sessions": "1"}, {"country": "Fiji", "sessions": "1"}, {"country": "Cambodia", "sessions": "1"}, {"country": "Mauritius", "sessions": "1"}, {"country": "Barbados", "sessions": "1"}, {"country": "Cyprus", "sessions": "1"}, {"country": "Mozambique", "sessions": "1"}, {"country": "Libya", "sessions": "1"}, {"country": "Zambia", "sessions": "1"}, {"country": "Ghana", "sessions": "1"}, {"country": "Kazakhstan", "sessions": "1"}, {"country": "Uzbekistan", "sessions": "1"}, {"country": "Tanzania", "sessions": "1"}, {"country": "Belarus", "sessions": "1"}, {"country": "Tunisia", "sessions": "1"}, {"country": "Aruba", "sessions": "1"}, {"country": "Lithuania", "sessions": "1"}, {"country": "Reunion", "sessions": "1"}, {"country": "[Unknown]", "sessions": "277"}]